README.md
setup.py
reloon/__init__.py
reloon.egg-info/PKG-INFO
reloon.egg-info/SOURCES.txt
reloon.egg-info/dependency_links.txt
reloon.egg-info/not-zip-safe
reloon.egg-info/top_level.txt