Metadata-Version: 1.0
Name: reloon
Version: 0.2.0
Summary: A collection of various Python regular expressions
Home-page: https://github.com/neuront/python-reloon
Author: Neuron Teckid
Author-email: lene13@gmail.com
License: BSD
Keywords: Python Regex Collection
Platform: UNKNOWN
